.gitignore
MANIFEST.in
setup.py
django_events.egg-info/PKG-INFO
django_events.egg-info/SOURCES.txt
django_events.egg-info/dependency_links.txt
django_events.egg-info/not-zip-safe
django_events.egg-info/top_level.txt
events/LICENSE.txt
events/README.rst
events/__init__.py
events/__init__.pyc
events/admin.py
events/admin.pyc
events/forms.py
events/forms.pyc
events/models.py
events/models.pyc
events/tests.py
events/urls.py
events/urls.pyc
events/views.py
events/views.pyc
events/media/css/events_form.css
events/media/css/jq-ui.css
events/media/css/jquery-ui.css
events/media/css/scrollable-minimal.css
events/media/css/scrollable-navig.css
events/media/css/ui.timepickr.css
events/media/css/images/ui-bg_flat_0_aaaaaa_40x100.png
events/media/css/images/ui-bg_flat_30_cccccc_40x100.png
events/media/css/images/ui-bg_flat_50_5c5c5c_40x100.png
events/media/css/images/ui-bg_flat_75_ffffff_40x100.png
events/media/css/images/ui-bg_glass_20_000000_1x400.png
events/media/css/images/ui-bg_glass_40_c44e00_1x400.png
events/media/css/images/ui-bg_glass_40_de5e6c_1x400.png
events/media/css/images/ui-bg_glass_55_fbf9ee_1x400.png
events/media/css/images/ui-bg_glass_65_ffffff_1x400.png
events/media/css/images/ui-bg_glass_75_dadada_1x400.png
events/media/css/images/ui-bg_glass_75_e6e6e6_1x400.png
events/media/css/images/ui-bg_glass_95_fef1ec_1x400.png
events/media/css/images/ui-bg_gloss-wave_25_000000_500x100.png
events/media/css/images/ui-bg_highlight-soft_75_cccccc_1x100.png
events/media/css/images/ui-bg_highlight-soft_80_eeeeee_1x100.png
events/media/css/images/ui-bg_inset-soft_25_000000_1x100.png
events/media/css/images/ui-bg_inset-soft_30_8b8543_1x100.png
events/media/css/images/ui-icons_161413_256x240.png
events/media/css/images/ui-icons_222222_256x240.png
events/media/css/images/ui-icons_2e83ff_256x240.png
events/media/css/images/ui-icons_454545_256x240.png
events/media/css/images/ui-icons_4b8e0b_256x240.png
events/media/css/images/ui-icons_888888_256x240.png
events/media/css/images/ui-icons_cd0a0a_256x240.png
events/media/css/images/ui-icons_ffffff_256x240.png
events/media/img/add.png
events/media/img/ajax_loader.gif
events/media/img/change.png
