Metadata-Version: 1.0
Name: django-events
Version: 0.1
Summary: django-events
Home-page: http://github.com/skyl/django-events
Author: Skylar Saveland
Author-email: skylar.saveland@gmail.com
License: MIT
Keywords: django,pinax,jquery-ui,datepickr
Platform: UNKNOWN
Classifier: Programming Language :: Python
Classifier: Topic :: Software Development :: Libraries :: Python Modules
Classifier: Framework :: Django
Classifier: Environment :: Web Environment
